report_generator.py
financial_report-0.1.0.dist-info/METADATA
financial_report-0.1.0.dist-info/WHEEL
financial_report-0.1.0.dist-info/top_level.txt
financial_report-0.1.0.dist-info/RECORD
