Metadata-Version: 2.1
Name: financial_report
Version: 0.1.0
Summary: Пакет для анализа финансовых транзакций.
Author-email: Menzurka <islamovri@menzurka.com>
Requires-Dist: pandas
